<?xml version="1.0" encoding="utf-8"?>
<TextureAtlas imagePath="DIO.png">
	<!-- Created with Adobe Animate version 21.0.6.41649 -->
	<!-- http://www.adobe.com/products/animate.html -->
	<SubTexture name="DIO Black Lines0000" x="0" y="0" width="1340" height="955"/>
	<SubTexture name="DIO Black Lines0001" x="1340" y="0" width="1340" height="955"/>
	<SubTexture name="DIO Black Lines0002" x="2680" y="0" width="1340" height="955"/>
	<SubTexture name="DIO Black Lines0003" x="0" y="955" width="1340" height="955"/>
	<SubTexture name="DIO Black Lines0004" x="1340" y="955" width="1340" height="955"/>
	<SubTexture name="DIO Black Lines0005" x="1340" y="955" width="1340" height="955"/>
	<SubTexture name="DIO Black Lines0006" x="1340" y="955" width="1340" height="955"/>
	<SubTexture name="DIO Black Lines0007" x="1340" y="955" width="1340" height="955"/>
	<SubTexture name="DIO Black Lines0008" x="1340" y="955" width="1340" height="955"/>
	<SubTexture name="DIO Black Lines0009" x="1340" y="955" width="1340" height="955"/>
	<SubTexture name="DIO Black Lines0010" x="1340" y="955" width="1340" height="955"/>
	<SubTexture name="DIO Black Lines0011" x="1340" y="955" width="1340" height="955"/>
	<SubTexture name="DIO Black Lines0012" x="1340" y="955" width="1340" height="955"/>
	<SubTexture name="DIO Black Lines0013" x="1340" y="955" width="1340" height="955"/>
	<SubTexture name="DIO Black Lines0014" x="1340" y="955" width="1340" height="955"/>
</TextureAtlas>
